<?xml version="1.0"?>
<opencv_storage>
<!-- Automatically converted from ./, window size = 40x30 -->
<handgesturehaar type_id="opencv-haar-classifier">
  <size>
    40 30</size>
  <stages>
    <_>
      <!-- stage 0 -->
      <trees>
        <_>
          <!-- tree 0 -->
          <_>
            <!-- root node -->
            <feature>
              <rects>
                <_>
                  13 0 2 2 -1.</_>
                <_>
                  13 0 1 1 2.</_>
                <_>
                  14 1 1 1 2.</_></rects>
              <tilted>0</tilted></feature>
            <threshold>-1.0677860118448734e-003</threshold>
            <left_val>9.9598801136016846e-001</left_val>
            <right_val>-9.8997461795806885e-001</right_val></_></_>
        <_>
          <!-- tree 1 -->
          <_>
            <!-- root node -->
            <feature>
              <rects>
                <_>
                  2 0 4 2 -1.</_>
                <_>
                  2 0 2 1 2.</_>
                <_>
                  4 1 2 1 2.</_></rects>
              <tilted>0</tilted></feature>
            <threshold>-1.7113389912992716e-003</threshold>
            <left_val>9.7686082124710083e-001</left_val>
            <right_val>-9.9999111890792847e-001</right_val></_></_></trees>
      <stage_threshold>-1.3113739900290966e-002</stage_threshold>
      <parent>-1</parent>
      <next>-1</next></_>
    <_>
      <!-- stage 1 -->
      <trees>
        <_>
          <!-- tree 0 -->
          <_>
            <!-- root node -->
            <feature>
              <rects>
                <_>
                  0 0 1 3 -1.</_>
                <_>
                  0 1 1 1 3.</_></rects>
              <tilted>0</tilted></feature>
            <threshold>-7.6924107270315289e-004</threshold>
            <left_val>1.</left_val>
            <right_val>-9.9994397163391113e-001</right_val></_></_></trees>
      <stage_threshold>1.</stage_threshold>
      <parent>0</parent>
      <next>-1</next></_></stages></handgesturehaar>
</opencv_storage>
